{
    "en": {
        "username": "Username",
        "email": "Email Address",
        "age-range": "Age Range",
        "password": "Password",
        "confirm-password": "Confirm Password",
        "new-password": "New Password",
        "dates-available": "Dates Available",
        "is-eligible-in-dlsu": "Are you an alumni, student, or faculty at De La Salle University - Manila?",
        "privacy-policy": "Privacy Policy",
        "keyboard-layout": "Keyboard Layout",
        "show-wpm": "Show WPM",
        "1st-week": "First week of November 2022",
        "2nd-week": "Second week of November 2022",
        "3rd-week": "Third week of November 2022",
        "4th-week": "Fourth week of November 2022",
        "yes": "Yes",
        "no": "No",
        "13-19": "13-19", 
        "20-29": "20-29",
        "30+": "30+",
        "privacy-email": "By registering an account, you are giving consent to typhe and agreeing to their <a class='text-blue-500 underline' target='_blank' href='/privacy-policy'>Privacy Policy</a>, and in compliance with the Data Privacy Act of 2012 (RA10173) and its Implementing Rules and Regulations (IPR) effective since September 9, 2016, I am authorizing these student researchers to: <ul class='list-decimal list-inside'> <li> Use my personal data, which includes my name, and age range , gathered for their undergraduate thesis. </li>   <li>Store my personal data for the analysis of results and the accomplishment of their undergraduate thesis.</li> </ul> By submitting, you are agreeing with the terms above. Rest assured your data will be used only for the reasons listed above and only by the entities stated in this terms.",
        "qwerty": "QWERTY",
        "salvo": "Salvo", 
        "dvorak": "Dvorak", 
        "iteration-1": "Unang iterasyon",
        "iteration-2": "Ikalawang iterasyon"
    },
    "fil": {
        "username": "Username",
        "email": "Sulatroniko",
        "age-range": "Hanay ng Edad",
        "password": "Password",
        "confirm-password": "Kumpirmahin ang Password",
        "new-password": "Bagong Password",
        "dates-available": "Mga Araw na Bakante",
        "is-eligible-in-dlsu": "Isa ka bang alumni, studyante, o faculty ng De La Salle University - Manila?",
        "privacy-policy": "Privacy Policy",
        "keyboard-layout": "Pagkakaayos ng Keyboard",
        "show-wpm": "Ipakita ang WPM",
        "1st-week": "Unang linggo ng Nobyembre 2022",
        "2nd-week": "Ikalawang linggo ng Nobyembre 2022",
        "3rd-week": "Ikatlong linggo ng Nobyembre 2022",
        "4th-week": "Ika-apat na linggo ng Nobyembre 2022",
        "yes": "Oo",
        "no": "Hindi",
        "13-19": "13-19", 
        "20-29": "20-29",
        "30+": "30+",
        "privacy-email": "Sa pagrehistro ng akawnt, binibigyan mo ng pahintulot ang typhe at sumasang-ayon ka sa kanilang <a class='text-blue-500 underline' target='_blank' href='/privacy-policy'>Patakaran sa Privacy</a>, at sa pagsunod ng Data Privacy Act of 2012 (RA10173) at ang kanyang Implementing Rules and Regulations (IPR) epektibo mula Septiyembre 9, 2016, pinahihintulutan mo ang mga estudyante sa:<ul class='list-decimal list-inside'> <li> Paggamit ng personal na datos katulad ng iyong pangalan, at hanay ng iyong edad, na nakuha para sa kanilang undergraduate thesis. </li>   <li>Pagipon ng iyong personal na datos para sa pagsusuri ng mga resulta para sa kanilang undergraduate thesis.</li> </ul> Sa pagpapasa, sumasangayon ka sa mga mga tuntunin sa itaas. Sinisigurado namin na ang mga datos na ibinigay mo ay gagamitin lang para sa mga rason na ibinahagi sa itaas at sa mga tao lang na nagsaad ng mga tuntunin na ito.",
        "qwerty": "QWERTY",
        "salvo": "Salvo", 
        "dvorak": "Dvorak", 
        "iteration-1": "First Iteration",
        "iteration-2": "Second Iteration"
    }
}
